hasi/__init__.py
hasi/align.py
hasi/classify.py
hasi/diffeoregistrar.py
hasi/meansquaresregistrar.py
hasi/meshtomeshregistrar.py
hasi/pointsetentropyregistrar.py
hasi-0.3.0.dist-info/LICENSE
hasi-0.3.0.dist-info/WHEEL
hasi-0.3.0.dist-info/METADATA
hasi-0.3.0.dist-info/RECORD
