Metadata-Version: 2.1
Name: hasi
Version: 0.3.0
Summary: High-throughput Applications for Skeletal Imaging (HASI) Python content
Home-page: https://github.com/KitwareMedical/HASI
License: UNKNOWN
Author: Kitware Medical
Author-email: matt.mccormick@kitware.com
Requires-Python: >=3.7
Classifier: License :: OSI Approved :: Apache Software License
Classifier: Programming Language :: Python :: 3
Classifier: Programming Language :: C++
Classifier: Development Status :: 4 - Beta
Classifier: Intended Audience :: Developers
Classifier: Intended Audience :: Education
Classifier: Intended Audience :: Healthcare Industry
Classifier: Intended Audience :: Science/Research
Classifier: Topic :: Scientific/Engineering
Classifier: Topic :: Scientific/Engineering :: Medical Science Apps.
Classifier: Topic :: Scientific/Engineering :: Information Analysis
Classifier: Topic :: Software Development :: Libraries
Classifier: Operating System :: Microsoft :: Windows
Classifier: Operating System :: Unix
Classifier: Operating System :: MacOS
Requires-Dist: itk-hasi>=0.2.2
Requires-Dist: itk-shape>=0.2.1
Requires-Dist: dwd>=1.0.1
Requires-Dist: pytest >=6.2.1 ; extra == "test"
Provides-Extra: test
